PyMultiDictionary/__init__.py
PyMultiDictionary/_dictionary.py
PyMultiDictionary/_goslate.py
PyMultiDictionary/_tokenizer.py
PyMultiDictionary/_utils.py
PyMultiDictionary/version.py
pymultidictionary-1.3.2.dist-info/LICENSE
pymultidictionary-1.3.2.dist-info/METADATA
pymultidictionary-1.3.2.dist-info/WHEEL
pymultidictionary-1.3.2.dist-info/top_level.txt
pymultidictionary-1.3.2.dist-info/RECORD
