Metadata-Version: 2.1
Name: pymultidictionary
Version: 1.3.2
Summary: PyMultiDictionary is a Dictionary Module for Python 2 to get meanings, translations, synonyms and antonyms of words in 20 different languages
Home-page: https://github.com/ppizarror/PyMultiDictionary
Author: Pablo Pizarro R.
Author-email: pablo@ppizarror.com
License: MIT
Project-URL: Bug Tracker, https://github.com/ppizarror/PyMultiDictionary
Project-URL: Documentation, https://github.com/ppizarror/PyMultiDictionary
Project-URL: Source Code, https://github.com/ppizarror/PyMultiDictionary
Keywords: dictionary multi-language synonym antonym definition
Platform: any
Classifier: License :: OSI Approved :: MIT License
Classifier: Natural Language :: English
Classifier: Operating System :: OS Independent
Classifier: Programming Language :: Python :: 3.7
Classifier: Programming Language :: Python :: 3.8
Classifier: Programming Language :: Python :: 3.9
Classifier: Programming Language :: Python :: 3.10
Classifier: Programming Language :: Python :: 3.11
Classifier: Programming Language :: Python :: 3.12
Classifier: Programming Language :: Python
Classifier: Topic :: Multimedia
Classifier: Topic :: Text Processing
Requires-Python: >=3.7, <4
License-File: LICENSE
Requires-Dist: bs4
Requires-Dist: iso639-lang
Requires-Dist: requests
Provides-Extra: docs
Requires-Dist: sphinx<7; extra == "docs"
Requires-Dist: sphinx-autodoc-typehints>=1.2.0; extra == "docs"
Requires-Dist: sphinx-rtd-theme; extra == "docs"
Provides-Extra: test
Requires-Dist: nose2[coverage_plugin]; extra == "test"
Requires-Dist: pytest; extra == "test"
